promptvibe/__init__.py
promptvibe/__main__.py
promptvibe/app.py
promptvibe-0.2.2.dist-info/LICENSE
promptvibe-0.2.2.dist-info/METADATA
promptvibe-0.2.2.dist-info/WHEEL
promptvibe-0.2.2.dist-info/entry_points.txt
promptvibe-0.2.2.dist-info/RECORD
