Metadata-Version: 2.3
Name: promptvibe
Version: 0.2.2
Summary: Optimize the user prompt
License: Apache Licence 2
Author: Praveen Govindaraj
Author-email: 38414524+Praveengovianalytics@users.noreply.github.com
Requires-Python: >=3.11,<3.14
Classifier: License :: Other/Proprietary License
Classifier: Programming Language :: Python :: 3
Classifier: Programming Language :: Python :: 3.11
Classifier: Programming Language :: Python :: 3.12
Classifier: Programming Language :: Python :: 3.13
Requires-Dist: dspy (>=2.6.27,<3.0.0)
Requires-Dist: gradio (>=5.33.0,<6.0.0)
